modelstore/__init__.py
modelstore/__main__.py
modelstore/model_store.py
modelstore/ids/__init__.py
modelstore/ids/model_ids.py
modelstore/metadata/__init__.py
modelstore/metadata/metadata.py
modelstore/metadata/code/__init__.py
modelstore/metadata/code/code.py
modelstore/metadata/code/dependencies.py
modelstore/metadata/code/revision.py
modelstore/metadata/code/runtime.py
modelstore/metadata/dataset/__init__.py
modelstore/metadata/dataset/dataset.py
modelstore/metadata/dataset/features.py
modelstore/metadata/dataset/labels.py
modelstore/metadata/dataset/types.py
modelstore/metadata/model/__init__.py
modelstore/metadata/model/model.py
modelstore/metadata/model/model_type.py
modelstore/metadata/storage/__init__.py
modelstore/metadata/storage/storage.py
modelstore/metadata/utils/__init__.py
modelstore/metadata/utils/utils.py
modelstore/models/__init__.py
modelstore/models/annoy.py
modelstore/models/catboost.py
modelstore/models/causalml.py
modelstore/models/common.py
modelstore/models/fastai.py
modelstore/models/gensim.py
modelstore/models/lightgbm.py
modelstore/models/managers.py
modelstore/models/missing_manager.py
modelstore/models/model_file.py
modelstore/models/model_manager.py
modelstore/models/multiple_models.py
modelstore/models/onnx.py
modelstore/models/prophet.py
modelstore/models/pyspark.py
modelstore/models/pytorch.py
modelstore/models/pytorch_lightning.py
modelstore/models/shap.py
modelstore/models/sklearn.py
modelstore/models/skorch.py
modelstore/models/tensorflow.py
modelstore/models/transformers.py
modelstore/models/util.py
modelstore/models/xgboost.py
modelstore/storage/__init__.py
modelstore/storage/aws.py
modelstore/storage/azure.py
modelstore/storage/blob_storage.py
modelstore/storage/gcloud.py
modelstore/storage/hdfs.py
modelstore/storage/local.py
modelstore/storage/minio.py
modelstore/storage/storage.py
modelstore/storage/states/__init__.py
modelstore/storage/states/model_states.py
modelstore/storage/util/__init__.py
modelstore-0.0.81.dist-info/LICENSE
modelstore-0.0.81.dist-info/METADATA
modelstore-0.0.81.dist-info/WHEEL
modelstore-0.0.81.dist-info/entry_points.txt
modelstore-0.0.81.dist-info/top_level.txt
modelstore-0.0.81.dist-info/RECORD
